melib/__init__.py
melib/excel.py
melib/library.py
melib/xt.py
melib/data/bearing.xlsx
melib/data/mats.xlsx
melib/data/sgear.xlsx
melib/data/shaft.xlsx
melib/data/vbelt.xlsx
melib-1.1.1.data/data/data/bearing.xlsx
melib-1.1.1.data/data/data/mats.xlsx
melib-1.1.1.data/data/data/sgear.xlsx
melib-1.1.1.data/data/data/shaft.xlsx
melib-1.1.1.data/data/data/vbelt.xlsx
melib-1.1.1.dist-info/LICENSE
melib-1.1.1.dist-info/METADATA
melib-1.1.1.dist-info/WHEEL
melib-1.1.1.dist-info/top_level.txt
melib-1.1.1.dist-info/RECORD
