Metadata-Version: 2.1
Name: melib
Version: 1.1.1
Summary: Library functions to help with machine element design projects.
Home-page: https://github.com/Gurgenci/melib
Author: Hal Gurgenci
Author-email: h.gurgenci@uq.edu.au
License: UNKNOWN
Platform: UNKNOWN
Classifier: Programming Language :: Python :: 3
Classifier: License :: OSI Approved :: GNU General Public License (GPL)
Classifier: Operating System :: OS Independent
Requires-Python: >=3.0
License-File: LICENSE
